{
  "id": "3c9a1e77-52b4-4f0d-8a6b-9d4e2c6f1a08",
  "name": "FirstClub Local",
  "values": [
    {
      "key": "baseUrl",
      "value": "http://localhost:8080",
      "type": "default",
      "enabled": true
    },
    {
      "key": "adminBootstrapSecret",
      "value": "local-dev-admin-bootstrap",
      "type": "secret",
      "enabled": true
    },
    {
      "key": "userId",
      "value": "7001",
      "type": "default",
      "enabled": true
    },
    {
      "key": "selfToken",
      "value": "",
      "type": "secret",
      "enabled": true
    },
    {
      "key": "adminToken",
      "value": "",
      "type": "secret",
      "enabled": true
    },
    {
      "key": "planId",
      "value": "",
      "type": "default",
      "enabled": true
    },
    {
      "key": "tierId",
      "value": "",
      "type": "default",
      "enabled": true
    },
    {
      "key": "goldTierId",
      "value": "",
      "type": "default",
      "enabled": true
    },
    {
      "key": "platinumTierId",
      "value": "",
      "type": "default",
      "enabled": true
    },
    {
      "key": "subscriptionId",
      "value": "",
      "type": "default",
      "enabled": true
    },
    {
      "key": "subscribeIdemKey",
      "value": "",
      "type": "default",
      "enabled": true
    }
  ],
  "_postman_variable_scope": "environment"
}
